MANIFEST.in
README.md
requirements.txt
setup.py
etl.ohlcv.egg-info/PKG-INFO
etl.ohlcv.egg-info/SOURCES.txt
etl.ohlcv.egg-info/dependency_links.txt
etl.ohlcv.egg-info/requires.txt
etl.ohlcv.egg-info/top_level.txt
etl/ohlcv/__init__.py
etl/ohlcv/__main__.py
etl/ohlcv/core.py
etl/ohlcv/logging.py
etl/ohlcv/table.py
etl/ohlcv/timeframe.py
etl/ohlcv/timeunit.py
etl/ohlcv/typing.py
etl/ohlcv/util/__init__.py
etl/ohlcv/util/datetime_util.py
etl/ohlcv/util/string_util.py
requirements/base.txt
requirements/dev.txt
requirements/test.txt