Metadata-Version: 2.1
Name: etl.ohlcv
Version: 0.2.0
Summary: etl-ohlcv CLI.
Author: Quantitative Developers
License: UNKNOWN
Platform: UNKNOWN
Requires-Python: >=3.7
